_librabbitmq.cpython-313t-x86_64-linux-gnu.so
funtests/__init__.py
funtests/config.py
funtests/disabled_basic_get_leak.py
funtests/setup.py
funtests/tests/__init__.py
funtests/tests/test_channel_errors.py
librabbitmq/__init__.py
librabbitmq_fork-2.0.2.dev3.dist-info/METADATA
librabbitmq_fork-2.0.2.dev3.dist-info/WHEEL
librabbitmq_fork-2.0.2.dev3.dist-info/top_level.txt
librabbitmq_fork-2.0.2.dev3.dist-info/RECORD
librabbitmq_fork-2.0.2.dev3.dist-info/licenses/AUTHORS
librabbitmq_fork-2.0.2.dev3.dist-info/licenses/LICENSE-GPL-2.0
librabbitmq_fork-2.0.2.dev3.dist-info/licenses/LICENSE-MPL-RabbitMQ
