Metadata-Version: 2.4
Name: librabbitmq-fork
Version: 2.0.2.dev3
Summary: AMQP Client using the rabbitmq-c library.
Home-page: http://github.com/henryykt/librabbitmq
Author: Ask Solem,Henry Tang
Author-email: ask@celeryproject.org,henryykt@gmail.com
License: MPL
Classifier: Development Status :: 5 - Production/Stable
Classifier: Operating System :: POSIX
Classifier: Operating System :: Microsoft :: Windows
Classifier: Programming Language :: C
Classifier: Programming Language :: Python :: 3.6
Classifier: Programming Language :: Python :: 3.8
Classifier: Programming Language :: Python :: 3.9
Classifier: Programming Language :: Python :: 3.10
Classifier: Programming Language :: Python :: 3.11
Classifier: Programming Language :: Python :: 3.12
Classifier: Programming Language :: Python :: 3.13
Classifier: Programming Language :: Python :: 3.14
Classifier: Programming Language :: Python :: Implementation :: CPython
Classifier: Intended Audience :: Developers
Classifier: License :: OSI Approved :: Mozilla Public License 1.0 (MPL)
Classifier: Topic :: Communications
Classifier: Topic :: System :: Networking
Classifier: Topic :: Software Development :: Libraries
License-File: LICENSE-GPL-2.0
License-File: LICENSE-MPL-RabbitMQ
License-File: AUTHORS
Requires-Dist: amqp>=1.4.6
Dynamic: author
Dynamic: author-email
Dynamic: classifier
Dynamic: description
Dynamic: home-page
Dynamic: license
Dynamic: license-file
Dynamic: requires-dist
Dynamic: summary
